rebullet/__init__.py
rebullet/charDef.py
rebullet/client.py
rebullet/colors.py
rebullet/cursor.py
rebullet/emojis.py
rebullet/exceptions.py
rebullet/keyhandler.py
rebullet/styles.py
rebullet/utils.py
rebullet/wrap_text.py
rebullet-2.4.1.dist-info/LICENSE
rebullet-2.4.1.dist-info/METADATA
rebullet-2.4.1.dist-info/WHEEL
rebullet-2.4.1.dist-info/top_level.txt
rebullet-2.4.1.dist-info/RECORD
