Metadata-Version: 2.1
Name: rebullet
Version: 2.4.1
Summary: Beautiful Python prompts made simple.
Home-page: https://github.com/h4rldev/rebullet
Author: bchao1, h4rldev and Maintainers
License: MIT
Keywords: cli list prompt customize colors
Classifier: Development Status :: 3 - Alpha
Classifier: Intended Audience :: Developers
Classifier: License :: OSI Approved :: MIT License
Classifier: Programming Language :: Python :: 3.10
Requires-Python: >=3.10
License-File: LICENSE
Requires-Dist: python-dateutil
